{
  "user": [
    "user-center.innerapi.aiAgent.getAdminInformation",
    "user-center.innerapi.aiAgent.modifyAdminInformation",
    "user-center.innerapi.aiAgent.modifyJobNumber",
    "user-center.innerapi.aiAgent.logMessage",
    "user-center.innerapi.aiAgent.getEnterpriseInformation",
    "user-center.innerapi.aiAgent.modifyEnterpriseInformation",
    "user-center.innerapi.aiAgent.foundationEnterprise.logMessage"
  ],
  "结果": [
    "user-center.innerapi.aiAgent.getAdminInformation",
    "user-center.innerapi.aiAgent.modifyAdminInformation",
    "user-center.innerapi.aiAgent.modifyJobNumber",
    "user-center.innerapi.aiAgent.logMessage",
    "user-center.innerapi.aiAgent.getEnterpriseInformation",
    "user-center.innerapi.aiAgent.modifyEnterpriseInformation",
    "user-center.innerapi.aiAgent.foundationEnterprise.logMessage"
  ],
  "dmi": [
    "user-center.innerapi.aiAgent.getAdminInformation",
    "user-center.innerapi.aiAgent.modifyAdminInformation",
    "user-center.innerapi.aiAgent.logMessage"
  ],
  "orm": [
    "user-center.innerapi.aiAgent.getAdminInformation",
    "user-center.innerapi.aiAgent.modifyAdminInformation",
    "user-center.innerapi.aiAgent.getEnterpriseInformation",
    "user-center.innerapi.aiAgent.modifyEnterpriseInformation"
  ],
  "dif": [
    "user-center.innerapi.aiAgent.modifyAdminInformation",
    "user-center.innerapi.aiAgent.modifyJobNumber",
    "user-center.innerapi.aiAgent.modifyEnterpriseInformation"
  ],
  "num": [
    "user-center.innerapi.aiAgent.modifyJobNumber"
  ],
  "处理modifyjobnumber并返回结果": [
    "user-center.innerapi.aiAgent.modifyJobNumber"
  ],
  "info": [
    "user-center.innerapi.aiAgent.logMessage",
    "user-center.innerapi.aiAgent.foundationEnterprise.logMessage"
  ],
  "变更": [
    "user-center.innerapi.aiAgent.logMessage",
    "user-center.innerapi.aiAgent.foundationEnterprise.logMessage"
  ],
  "人名称": [
    "user-center.innerapi.aiAgent.logMessage"
  ],
  "og": [
    "user-center.innerapi.aiAgent.logMessage",
    "user-center.innerapi.aiAgent.foundationEnterprise.logMessage"
  ],
  "企业": [
    "user-center.innerapi.aiAgent.getEnterpriseInformation",
    "user-center.innerapi.aiAgent.modifyEnterpriseInformation",
    "user-center.innerapi.aiAgent.foundationEnterprise.logMessage"
  ]
}
